CloudComputing/__init__.py
CloudComputing/cc_debug.py
CloudComputing/cloud_storage.py
CloudComputing/config.py
CloudComputing/remote_exec.py
CloudComputing/vars.py
CloudComputing-0.4.1.dist-info/LICENSE
CloudComputing-0.4.1.dist-info/METADATA
CloudComputing-0.4.1.dist-info/WHEEL
CloudComputing-0.4.1.dist-info/top_level.txt
CloudComputing-0.4.1.dist-info/RECORD
