Metadata-Version: 2.1
Name: CloudComputing
Version: 0.4.1
Summary: CloudComputing package
Home-page: https://github.com/mp1994/CloudComputing
Author: Mattia Pesenti
Author-email: <mattia.pesenti@gmail.com>
License: UNKNOWN
Keywords: python,cloud computing,onedrive
Platform: UNKNOWN
Classifier: Development Status :: 3 - Alpha
Classifier: Intended Audience :: Developers
Classifier: Programming Language :: Python :: 3
Classifier: Operating System :: MacOS :: MacOS X
Classifier: Operating System :: POSIX :: Linux
Requires-Dist: cloudsync
Requires-Dist: cloudsync-onedrive
Requires-Dist: pytest
